odoo/addons/l10n_es_aeat_mod303_oss/README.rst
odoo/addons/l10n_es_aeat_mod303_oss/__init__.py
odoo/addons/l10n_es_aeat_mod303_oss/__manifest__.py
odoo/addons/l10n_es_aeat_mod303_oss/data/tax_code_map_mod303_data.xml
odoo/addons/l10n_es_aeat_mod303_oss/i18n/l10n_es_aeat_mod303_oss.pot
odoo/addons/l10n_es_aeat_mod303_oss/models/__init__.py
odoo/addons/l10n_es_aeat_mod303_oss/models/mod303.py
odoo/addons/l10n_es_aeat_mod303_oss/readme/CONTRIBUTORS.rst
odoo/addons/l10n_es_aeat_mod303_oss/readme/DESCRIPTION.rst
odoo/addons/l10n_es_aeat_mod303_oss/static/description/icon.png
odoo/addons/l10n_es_aeat_mod303_oss/static/description/icon_source.svg
odoo/addons/l10n_es_aeat_mod303_oss/static/description/index.html
odoo/addons/l10n_es_aeat_mod303_oss/tests/__init__.py
odoo/addons/l10n_es_aeat_mod303_oss/tests/test_l10n_es_aeat_mod303_oss.py
odoo12_addon_l10n_es_aeat_mod303_oss-12.0.1.0.0.99.dev3.dist-info/METADATA
odoo12_addon_l10n_es_aeat_mod303_oss-12.0.1.0.0.99.dev3.dist-info/WHEEL
odoo12_addon_l10n_es_aeat_mod303_oss-12.0.1.0.0.99.dev3.dist-info/top_level.txt
odoo12_addon_l10n_es_aeat_mod303_oss-12.0.1.0.0.99.dev3.dist-info/RECORD
