Metadata-Version: 2.1
Name: odoo12-addon-l10n-es-aeat-mod303-oss
Version: 12.0.1.0.0.99.dev3
Summary: AEAT modelo 303 - OSS
Home-page: https://github.com/OCA/l10n-spain
Author: PESOL, Tecnativa, Odoo Community Association (OCA)
Author-email: support@odoo-community.org
License: AGPL-3
Platform: UNKNOWN
Classifier: Programming Language :: Python
Classifier: Framework :: Odoo
Classifier: Framework :: Odoo :: 12.0
Classifier: License :: OSI Approved :: GNU Affero General Public License v3
Requires-Python: >=3.5
Requires-Dist: odoo12-addon-l10n-es-aeat-mod303
Requires-Dist: odoo12-addon-l10n-eu-oss
Requires-Dist: odoo <12.1dev,>=12.0a
